Metadata-Version: 1.0
Name: pythontest
Version: 0.1.2
Summary: UNKNOWN
Home-page: https://github.com/snowroll/python-sdk.git
Author: Peng Shiyu
Author-email: pengshiyuyx@gmail.com
License: MIT License
Platform: UNKNOWN
